LICENSE
MANIFEST.in
README.md
setup.py
doxietodropbox/__init__.py
doxietodropbox/base.py
doxietodropbox/doxie.py
doxietodropbox/example.env
doxietodropbox/example.service
doxietodropbox/service.py
doxietodropbox/settings.py
doxietodropbox.egg-info/PKG-INFO
doxietodropbox.egg-info/SOURCES.txt
doxietodropbox.egg-info/dependency_links.txt
doxietodropbox.egg-info/requires.txt
doxietodropbox.egg-info/top_level.txt